[
  {
    "title": "monde:::En direct, Moyen-Orient – «Le monde assiste à un génocide» à Gaza, juge Amnesty International",
    "added_at": "2025-04-29T01:25:16.962Z",
    "removed_at": "2025-04-29T12:10:37.348Z",
    "duration_minutes": 645,
    "duration_str": "10h 45m"
  },
  {
    "title": "monde:::Panne massive dans la péninsule Ibérique: l’électricité a été rétablie à près de 90% en Espagne",
    "added_at": "2025-04-29T02:50:44.396Z",
    "removed_at": "2025-04-29T07:44:31.786Z",
    "duration_minutes": 294,
    "duration_str": "4h 54m"
  },
  {
    "title": "monde:::Le libéral Mark Carney est élu premier ministre du Canada, selon de premières projections",
    "added_at": "2025-04-29T03:09:20.713Z",
    "removed_at": "2025-04-29T03:44:43.401Z",
    "duration_minutes": 35,
    "duration_str": "35m"
  },
  {
    "title": "monde:::Le libéral Mark Carney élu premier ministre du Canada, selon de premières projections",
    "added_at": "2025-04-29T03:26:05.115Z",
    "removed_at": "2025-04-29T03:40:56.898Z",
    "duration_minutes": 15,
    "duration_str": "15m"
  },
  {
    "title": "monde:::Le libéral Mark Carney est élu premier ministre du Canada, selon les projections",
    "added_at": "2025-04-29T03:44:43.401Z",
    "removed_at": "2025-04-29T05:41:50.057Z",
    "duration_minutes": 117,
    "duration_str": "1h 57m"
  },
  {
    "title": "suisse:::Le Contrôle des finances estime que la stratégie fédérale sur la corruption doit être révisée et améliorée",
    "added_at": "2025-04-29T04:12:37.022Z",
    "removed_at": "2025-04-29T04:36:43.403Z",
    "duration_minutes": 24,
    "duration_str": "24m"
  },
  {
    "title": "monde:::Le droit international menacé par les conflits et les «attaques frontales» de Donald Trump, fustige Amnesty",
    "added_at": "2025-04-29T04:12:37.022Z",
    "removed_at": "2025-04-29T05:08:22.979Z",
    "duration_minutes": 56,
    "duration_str": "56m"
  },
  {
    "title": "suisse:::Le spectre d’une commission d’enquête parlementaire plane sur le Grand Conseil vaudois",
    "added_at": "2025-04-29T04:36:43.403Z",
    "removed_at": "2025-04-29T15:14:50.742Z",
    "duration_minutes": 638,
    "duration_str": "10h 38m"
  },
  {
    "title": "monde:::En Ukraine: «Notre Constitution ne permet pas de changements territoriaux»",
    "added_at": "2025-04-29T04:38:36.243Z",
    "duration_minutes": 0,
    "duration_str": ""
  },
  {
    "title": "monde:::Reconnaître l’annexion de la Crimée, «c’est ouvrir la boîte de Pandore»",
    "added_at": "2025-04-29T04:38:36.243Z",
    "removed_at": "2025-05-01T10:30:53.613Z",
    "duration_minutes": 3232,
    "duration_str": "2d 5h 52m"
  },
  {
    "title": "economie:::Pourquoi nous aimons soutenir des politiques irrationnelles",
    "added_at": "2025-04-29T05:04:36.889Z",
    "removed_at": "2025-04-29T13:17:40.200Z",
    "duration_minutes": 493,
    "duration_str": "8h 13m"
  },
  {
    "title": "suisse:::Christian Varone, commandant de la police valaisanne: «Avec notre ligne ferme, nous combattons le racisme et l’exclusion»",
    "added_at": "2025-04-29T05:08:22.979Z",
    "removed_at": "2025-04-29T19:20:23.777Z",
    "duration_minutes": 852,
    "duration_str": "14h 12m"
  },
  {
    "title": "monde:::Le Canada élit Mark Carney à sa tête pour croiser le fer avec Donald Trump",
    "added_at": "2025-04-29T05:41:50.057Z",
    "removed_at": "2025-04-30T04:27:20.476Z",
    "duration_minutes": 1366,
    "duration_str": "22h 46m"
  },
  {
    "title": "cyber:::Ultra-dominateur sur le web, le navigateur Chrome de Google intéresse les géants de l’intelligence artificielle",
    "added_at": "2025-04-29T06:07:49.317Z",
    "duration_minutes": 0,
    "duration_str": ""
  },
  {
    "title": "suisse:::Clarence Chollet: un nouveau souffle vert sur Berne",
    "added_at": "2025-04-29T06:35:42.460Z",
    "removed_at": "2025-04-29T13:21:22.638Z",
    "duration_minutes": 406,
    "duration_str": "6h 46m"
  },
  {
    "title": "suisse:::Le Val Maggia encore sonné, dix mois après les intempéries meurtrières",
    "added_at": "2025-04-29T07:20:18.802Z",
    "removed_at": "2025-04-29T19:53:52.540Z",
    "duration_minutes": 754,
    "duration_str": "12h 34m"
  },
  {
    "title": "economie:::Bénéfice et chiffre d’affaires en hausse pour Novartis qui survole les incertitudes économiques au premier trimestre",
    "added_at": "2025-04-29T07:44:31.786Z",
    "removed_at": "2025-04-29T09:39:51.683Z",
    "duration_minutes": 115,
    "duration_str": "1h 55m"
  },
  {
    "title": "sport:::Arsenal ou PSG, le Rwanda sera en finale de la Ligue des champions",
    "added_at": "2025-04-29T08:03:04.771Z",
    "removed_at": "2025-04-29T17:54:48.233Z",
    "duration_minutes": 592,
    "duration_str": "9h 52m"
  },
  {
    "title": "monde:::En direct, guerre en Ukraine – Donald Trump affirme vouloir «sauver» l’Ukraine, un pays «bientôt écrasé» par la Russie",
    "added_at": "2025-04-29T08:45:56.947Z",
    "removed_at": "2025-04-29T08:47:45.057Z",
    "duration_minutes": 2,
    "duration_str": "2m"
  },
  {
    "title": "monde:::En direct – Donald Trump affirme vouloir «sauver» l’Ukraine, un pays «bientôt écrasé» par la Russie",
    "added_at": "2025-04-29T08:47:45.057Z",
    "removed_at": "2025-04-30T04:23:40.380Z",
    "duration_minutes": 1176,
    "duration_str": "19h 36m"
  },
  {
    "title": "monde:::Cyril Hanouna fait son buzz sur une éventuelle candidature à la présidentielle française",
    "added_at": "2025-04-29T08:55:12.326Z",
    "removed_at": "2025-04-29T17:54:48.233Z",
    "duration_minutes": 540,
    "duration_str": "9h"
  },
  {
    "title": "cyber:::Hubert Guillaud, essayiste: «Nous devons modérer nos attentes à l’égard des algorithmes»",
    "added_at": "2025-04-29T09:39:51.683Z",
    "removed_at": "2025-04-29T11:16:43.309Z",
    "duration_minutes": 97,
    "duration_str": "1h 37m"
  },
  {
    "title": "sciences:::Les salles d’escalade sont saturées de substances toxiques, selon une étude de l’EPFL",
    "added_at": "2025-04-29T10:00:18.034Z",
    "removed_at": "2025-04-29T15:42:43.519Z",
    "duration_minutes": 342,
    "duration_str": "5h 42m"
  },
  {
    "title": "suisse:::Un avion frôle des randonneurs au Mont-Rose, le pilote s’excuse",
    "added_at": "2025-04-29T10:35:46.308Z",
    "removed_at": "2025-04-29T10:41:20.510Z",
    "duration_minutes": 6,
    "duration_str": "6m"
  },
  {
    "title": "suisse:::Le pilote d’un avion s’excuse après avoir frôlé des randonneurs au Mont-Rose",
    "added_at": "2025-04-29T10:41:20.510Z",
    "removed_at": "2025-04-29T19:20:23.777Z",
    "duration_minutes": 519,
    "duration_str": "8h 39m"
  },
  {
    "title": "suisse:::Le retrait qui sauve l’honneur du ministre jurassien David Eray",
    "added_at": "2025-04-29T11:18:31.456Z",
    "removed_at": "2025-04-29T19:20:23.777Z",
    "duration_minutes": 482,
    "duration_str": "8h 2m"
  },
  {
    "title": "monde:::En direct, Moyen-Orient – Accusé de «génocide», Israël condamne «les mensonges sans fondement» d’Amnesty",
    "added_at": "2025-04-29T12:10:37.348Z",
    "removed_at": "2025-04-29T15:59:28.619Z",
    "duration_minutes": 229,
    "duration_str": "3h 49m"
  },
  {
    "title": "monde:::La justice espagnole veut déterminer si un éventuel «sabotage informatique» a causé la panne électrique",
    "added_at": "2025-04-29T13:21:22.638Z",
    "removed_at": "2025-04-29T15:09:15.197Z",
    "duration_minutes": 108,
    "duration_str": "1h 48m"
  },
  {
    "title": "culture:::Avec «Les Indomptés», Daniel Minahan imagine sur grand écran des années 1950 plus libérées",
    "added_at": "2025-04-29T14:22:44.245Z",
    "removed_at": "2025-04-29T17:54:48.233Z",
    "duration_minutes": 212,
    "duration_str": "3h 32m"
  },
  {
    "title": "economie:::Amazon s’apprêterait à afficher le coût des droits de douane américains sur certains produits",
    "added_at": "2025-04-29T15:09:15.197Z",
    "removed_at": "2025-04-29T17:17:36.129Z",
    "duration_minutes": 128,
    "duration_str": "2h 8m"
  },
  {
    "title": "economie:::Un an après la porte arrachée en plein vol, Airbus s’empare d’une partie de Spirit AeroSystems",
    "added_at": "2025-04-29T15:14:50.742Z",
    "removed_at": "2025-04-29T20:14:19.422Z",
    "duration_minutes": 299,
    "duration_str": "4h 59m"
  },
  {
    "title": "suisse:::A Genève, le personnel de nettoyage de l’hôpital obtient des contrats à plein temps après des années de revendication",
    "added_at": "2025-04-29T15:42:43.519Z",
    "removed_at": "2025-04-30T15:05:34.678Z",
    "duration_minutes": 1403,
    "duration_str": "23h 23m"
  },
  {
    "title": "suisse:::Initiative sur le foie gras: restreindre l’importation plutôt que l’interdire? Débat sur un contre-projet indirect",
    "added_at": "2025-04-29T15:50:13.461Z",
    "removed_at": "2025-04-29T18:58:04.497Z",
    "duration_minutes": 188,
    "duration_str": "3h 8m"
  },
  {
    "title": "monde:::En direct, Moyen-Orient – «Des efforts internationaux doivent être déployés pour empêcher cette catastrophe humanitaire d'atteindre un nouveau niveau inégalé»",
    "added_at": "2025-04-29T15:59:28.619Z",
    "removed_at": "2025-04-29T17:47:25.496Z",
    "duration_minutes": 108,
    "duration_str": "1h 48m"
  },
  {
    "title": "monde:::En graphiques – Comment Donald Trump a pris le pouvoir en 100 jours et met au défi la démocratie américaine",
    "added_at": "2025-04-29T17:02:45.636Z",
    "duration_minutes": 0,
    "duration_str": ""
  },
  {
    "title": "economie:::Durant ses 100 premiers jours, Donald Trump a pris les investisseurs à revers",
    "added_at": "2025-04-29T17:08:20.121Z",
    "removed_at": "2025-04-30T09:30:38.435Z",
    "duration_minutes": 982,
    "duration_str": "16h 22m"
  },
  {
    "title": "economie:::Amazon n’affichera pas le coût des droits de douane américains sur certains produits",
    "added_at": "2025-04-29T17:17:36.129Z",
    "removed_at": "2025-04-30T07:35:11.667Z",
    "duration_minutes": 858,
    "duration_str": "14h 18m"
  },
  {
    "title": "monde:::Après la méga-coupure d’électricité, l’Espagne découvre la fragilité des énergies renouvelables",
    "added_at": "2025-04-29T17:25:05.119Z",
    "removed_at": "2025-05-01T17:29:39.480Z",
    "duration_minutes": 2885,
    "duration_str": "2d 5m"
  },
  {
    "title": "monde:::En direct, Moyen-Orient – Antonio Guterres: «Le monde ne peut pas se permettre de regarder la solution à deux Etats disparaître»",
    "added_at": "2025-04-29T17:47:25.496Z",
    "removed_at": "2025-04-30T02:46:54.008Z",
    "duration_minutes": 539,
    "duration_str": "8h 59m"
  },
  {
    "title": "sport:::«Quand on court chez soi, on est attendu au tournant»: souvenirs et rêves croisés sur le Tour de Romandie",
    "added_at": "2025-04-29T17:54:48.233Z",
    "removed_at": "2025-04-30T06:02:12.182Z",
    "duration_minutes": 727,
    "duration_str": "12h 7m"
  },
  {
    "title": "sport:::Samuel Watson, un maillot jaune de dernière minute après le prologue du Tour de Romandie",
    "added_at": "2025-04-29T17:54:48.233Z",
    "removed_at": "2025-04-29T19:18:31.738Z",
    "duration_minutes": 84,
    "duration_str": "1h 24m"
  },
  {
    "title": "monde:::Cyril Hanouna fait son buzz sur une éventuelle candidature à la présidentielle française, avant de démentir",
    "added_at": "2025-04-29T17:54:48.233Z",
    "removed_at": "2025-04-30T06:02:12.182Z",
    "duration_minutes": 727,
    "duration_str": "12h 7m"
  },
  {
    "title": "suisse:::Les parlementaires privilégient la voie du dialogue avec l’administration Trump… pour le moment",
    "added_at": "2025-04-29T18:11:32.799Z",
    "removed_at": "2025-05-01T04:09:25.173Z",
    "duration_minutes": 2038,
    "duration_str": "1d 9h 58m"
  },
  {
    "title": "monde:::Le renseignement militaire russe derrière le piratage de la campagne de Macron en 2017",
    "added_at": "2025-04-29T18:48:48.312Z",
    "removed_at": "2025-04-30T05:28:44.091Z",
    "duration_minutes": 640,
    "duration_str": "10h 40m"
  },
  {
    "title": "suisse:::La droite du Grand Conseil vaudois se mobilise de nouveau contre le loup",
    "added_at": "2025-04-29T18:58:04.497Z",
    "removed_at": "2025-05-01T04:14:59.698Z",
    "duration_minutes": 1997,
    "duration_str": "1d 9h 17m"
  },
  {
    "title": "culture:::En revenant à Astérix dans une série Netflix, Alain Chabat offre une nouvelle perle gauloise",
    "added_at": "2025-04-29T19:18:31.738Z",
    "removed_at": "2025-04-30T08:42:12.449Z",
    "duration_minutes": 804,
    "duration_str": "13h 24m"
  },
  {
    "title": "culture:::Notre guide avant de découvrir la nouvelle série d'Alain Chabat: les cinq meilleurs dessins animés d’Astérix",
    "added_at": "2025-04-29T19:18:31.738Z",
    "removed_at": "2025-04-29T22:15:22.622Z",
    "duration_minutes": 177,
    "duration_str": "2h 57m"
  },
  {
    "title": "economie:::Changement d’époque chez L’Oréal: Françoise Bettencourt Meyers passe la main à la nouvelle génération",
    "added_at": "2025-04-29T19:20:23.777Z",
    "removed_at": "2025-04-30T08:06:55.451Z",
    "duration_minutes": 767,
    "duration_str": "12h 47m"
  },
  {
    "title": "monde:::Les libéraux de Mark Carney échouent de peu à obtenir la majorité absolue au parlement canadien",
    "added_at": "2025-04-29T20:14:19.422Z",
    "removed_at": "2025-04-30T06:09:40.706Z",
    "duration_minutes": 595,
    "duration_str": "9h 55m"
  },
  {
    "title": "economie:::Les montres Corum reviennent en mains neuchâteloises",
    "added_at": "2025-04-29T22:39:29.532Z",
    "removed_at": "2025-04-30T12:55:15.420Z",
    "duration_minutes": 856,
    "duration_str": "14h 16m"
  }
]